qloud/__init__.py
qloud-0.0.1.dist-info/LICENSE
qloud-0.0.1.dist-info/METADATA
qloud-0.0.1.dist-info/WHEEL
qloud-0.0.1.dist-info/top_level.txt
qloud-0.0.1.dist-info/RECORD
