Metadata-Version: 2.1
Name: qloud
Version: 0.0.1
Summary: qloud
Home-page: https://github.com/JARVIS-Materials-Design/qloud
Author: Kamal Choudhary
Author-email: kamal.choudhary@nist.gov
License: UNKNOWN
Platform: UNKNOWN
Classifier: Programming Language :: Python :: 3
Classifier: License :: OSI Approved :: MIT License
Classifier: Operating System :: OS Independent
Requires-Python: >=3.6
